bag_convert/__init__.py
bag_convert/main.py
bag_convert/bag2record/__init__.py
bag_convert/bag2record/bag2record.py
bag_convert/bag2record/header.py
bag_convert/bag2record/imu.py
bag_convert/bag2record/localization.py
bag_convert/bag2record/pointcloud.py
bag_convert/bag2record/sensor_image.py
bag_convert/record2bag/__init__.py
bag_convert/record2bag/compressed_image.py
bag_convert/record2bag/header.py
bag_convert/record2bag/image.py
bag_convert/record2bag/imu.py
bag_convert/record2bag/pointcloud2.py
bag_convert/record2bag/pose.py
bag_convert/record2bag/record2bag.py
bag_convert-0.0.1.dist-info/LICENSE
bag_convert-0.0.1.dist-info/METADATA
bag_convert-0.0.1.dist-info/WHEEL
bag_convert-0.0.1.dist-info/entry_points.txt
bag_convert-0.0.1.dist-info/top_level.txt
bag_convert-0.0.1.dist-info/RECORD
