Metadata-Version: 2.1
Name: bag-convert
Version: 0.0.1
Summary: Ros bag to Apollo record or reverse conversion
Home-page: https://github.com/daohu527/bag_convert
Author: daohu527
Author-email: daohu527@gmail.com
Project-URL: Bug Tracker, https://github.com/daohu527/bag_convert/issues
Classifier: Programming Language :: Python :: 3
Classifier: License :: OSI Approved :: Apache Software License
Classifier: Operating System :: OS Independent
Requires-Python: >=3.6
License-File: LICENSE
Requires-Dist: cyber-record
Requires-Dist: record-msg (<=0.1.1)
Requires-Dist: py3rosmsgs
Requires-Dist: rospkg
Requires-Dist: pycryptodomex
